cz_github_jira_conventional.py
cz_github_jira_conventional-3.0.2.dist-info/licenses/LICENSE
cz_github_jira_conventional-3.0.2.dist-info/METADATA
cz_github_jira_conventional-3.0.2.dist-info/WHEEL
cz_github_jira_conventional-3.0.2.dist-info/entry_points.txt
cz_github_jira_conventional-3.0.2.dist-info/top_level.txt
cz_github_jira_conventional-3.0.2.dist-info/RECORD
