Metadata-Version: 2.4
Name: cz_github_jira_conventional
Version: 3.0.2
Summary: Extend the commitizen tools to create conventional commits and README that link to Jira and GitHub.
Home-page: https://github.com/apheris/cz-github-jira-conventional
Author: Falko Krause, apheris AI GmbH
Author-email: f.krause@apheris.com
License: MIT
License-File: LICENSE
Requires-Dist: commitizen>=4.7.2
Dynamic: author
Dynamic: author-email
Dynamic: description
Dynamic: description-content-type
Dynamic: home-page
Dynamic: license
Dynamic: license-file
Dynamic: requires-dist
Dynamic: summary
